{
  "id": "oscar-wilde-serenade-for-music",
  "title": "Serenade (For Music)",
  "author": "Oscar Wilde",
  "content": "The western wind is blowing fair\nAcross the dark AEgean sea,\nAnd at the secret marble stair\nMy Tyrian galley waits for thee.\nCome down! the purple sail is spread,\nThe watchman sleeps within the town,\nO leave thy lily-flowered bed,\nO Lady mine come down, come down!\n\nShe will not come, I know her well,\nOf lover's vows she hath no care,\nAnd little good a man can tell\nOf one so cruel and so fair.\nTrue love is but a woman's toy,\nThey never know the lover's pain,\nAnd I who loved as loves a boy\nMust love in vain, must love in vain.\n\nO noble pilot, tell me true,\nIs that the sheen of golden hair?\nOr is it but the tangled dew\nThat binds the passion-flowers there?\nGood sailor come and tell me now\nIs that my Lady's lily hand?\nOr is it but the gleaming prow,\nOr is it but the silver sand?\n\nNo! no! 'tis not the tangled dew,\n'Tis not the silver-fretted sand,\nIt is my own dear Lady true\nWith golden hair and lily hand!\nO noble pilot, steer for Troy,\nGood sailor, ply the labouring oar,\nThis is the Queen of life and joy\nWhom we must bear from Grecian shore!\n\nThe waning sky grows faint and blue,\nIt wants an hour still of day,\nAboard! aboard! my gallant crew,\nO Lady mine, away! away!\nO noble pilot, steer for Troy,\nGood sailor, ply the labouring oar,\nO loved as only loves a boy!\nO loved for ever evermore!",
  "source": "PoetryDB / Project Gutenberg",
  "linecount": 40
}