{
  "id": "james-weldon-johnson-morning-noon-and-night",
  "title": "MORNING, NOON AND NIGHT",
  "author": "James Weldon Johnson",
  "content": "When morning shows her first faint flush,\nI think of the tender blush\nThat crept so gently to your cheek\nWhen first my love I dared to speak;\nHow, in your glance, a dawning ray\nGave promise of love's perfect day.\n\nWhen, in the ardent breath of noon,\nThe roses with passion swoon;\nThere steals upon me from the air\nThe scent that lurked within your hair;\nI touch your hand, I clasp your form--\nAgain your lips are close and warm.\n\nWhen comes the night with beauteous skies,\nI think of your tear-dimmed eyes,\nTheir mute entreaty that I stay,\nAlthough your lips sent me away;\nAnd then falls memory's bitter blight,\nAnd dark--so dark becomes the night.",
  "source": "Project Gutenberg, Fifty Years & Other Poems (EBook #17884)",
  "date": "1917"
}