{
  "id": "james-weldon-johnson-the-awakening",
  "title": "THE AWAKENING",
  "author": "James Weldon Johnson",
  "content": "I dreamed that I was a rose\nThat grew beside a lonely way,\nClose by a path none ever chose,\nAnd there I lingered day by day.\nBeneath the sunshine and the show'r\nI grew and waited there apart,\nGathering perfume hour by hour,\nAnd storing it within my heart,\nYet, never knew,\nJust why I waited there and grew.\n\nI dreamed that you were a bee\nThat one day gaily flew along,\nYou came across the hedge to me,\nAnd sang a soft, love-burdened song.\nYou brushed my petals with a kiss,\nI woke to gladness with a start,\nAnd yielded up to you in bliss\nThe treasured fragrance of my heart;\nAnd then I knew\nThat I had waited there for you.",
  "source": "Project Gutenberg, Fifty Years & Other Poems (EBook #17884)",
  "date": "1917"
}