{
  "id": "james-weldon-johnson-de-little-pickaninnys-gone-to-sleep",
  "title": "DE LITTLE PICKANINNY'S GONE TO SLEEP",
  "author": "James Weldon Johnson",
  "content": "Cuddle down, ma honey, in yo' bed,\nGo to sleep an' res' yo' little head,\nBeen a-kind o' ailin' all de day?\nDidn't have no sperit fu' to play?\nNever min'; to-morrer, w'en you wek,\nDaddy's gwine to ride you on his bek,\n'Roun' an' roun' de cabin flo' so fas'--\nDer! He's closed his little eyes at las'.\n\nDe little pickaninny's gone to sleep,\nCuddled in his trundle bed so tiny,\nDe little pickaninny's gone to sleep,\nClosed his little eyes so bright an' shiny.\nHush! an' w'en you walk across de flo'\nStep across it very sof' an' slow.\nDe shadders all aroun' begin to creep,\nDe little pickaninny's gone to sleep.\n\nMandy, w'at's de matter wid dat chile?\nKeeps a-sighin' ev'y little w'ile;\nSeems to me I heayhd him sorter groan,\nLord! his little han's am col' as stone!\nW'at's dat far-off light dat's in his eyes?\nDat's a light dey's borrow'd f'om de skies;\nFol' his little han's across his breas',\nLet de little pickaninny res'.",
  "source": "Project Gutenberg, Fifty Years & Other Poems (EBook #17884)",
  "date": "1917"
}