{
  "id": "george-gordon-lord-byron-sonnet-to-the-prince-regent-on-the-repeal-of-lord-edward-fitzgeralds-forfeiture",
  "title": "Sonnet to the Prince Regent. on the Repeal of Lord Edward Fitzgerald's Forfeiture",
  "author": "George Gordon, Lord Byron",
  "content": "To be the father of the fatherless,\n  To stretch the hand from the throne's height, and raise\n  _His_ offspring, who expired in other days\nTo make thy Sire's sway by a kingdom less,--\n_This_ is to be a monarch, and repress\n  Envy into unutterable praise.\n  Dismiss thy guard, and trust thee to such traits,\nFor who would lift a hand, except to bless?\n  Were it not easy, Sir, and is't not sweet\n  To make thyself belovéd? and to be\nOmnipotent by Mercy's means? for thus\n  Thy Sovereignty would grow but more complete,\nA despot thou, and yet thy people free,\n  And by the heart--not hand--enslaving us.",
  "source": "PoetryDB / Project Gutenberg",
  "linecount": 14
}