{
  "id": "stephen-crane-when-a-people-reach-the-top-of-a-hill",
  "title": "When a people reach the top of a hill,",
  "author": "Stephen Crane",
  "content": "When a people reach the top of a hill,\nThen does God lean toward them,\nShortens tongues and lengthens arms.\nA vision of their dead comes to the weak.\nThe moon shall not be too old\nBefore the new battalions rise,\nBlue battalions.\nThe moon shall not be too old\nWhen the children of change shall fall\nBefore the new battalions,\nThe blue battalions.\n\nMistakes and virtues will be trampled deep.\nA church and a thief shall fall together.\nA sword will come at the bidding of the eyeless,\nThe God-led, turning only to beckon,\nSwinging a creed like a censer\nAt the head of the new battalions,\nBlue battalions.\nMarch the tools of nature's impulse,\nMen born of wrong, men born of right,\nMen of the new battalions,\nThe blue battalions.\n\nThe clang of swords is Thy wisdom,\nThe wounded make gestures like Thy Son's;\nThe feet of mad horses is one part --\nAy, another is the hand of a mother on the brow of a youth.\nThen, swift as they charge through a shadow,\nThe men of the new battalions,\nBlue battalions --\nGod lead them high, God lead them far,\nGod lead them far, God lead them high,\nThese new battalions,\nThe blue battalions.\n\nTHE END",
  "source": "PoetryDB / Project Gutenberg",
  "linecount": 34
}