{
  "id": "frances-harper-burial-of-sarah",
  "title": "Burial Of Sarah",
  "author": "Frances Ellen Watkins Harper",
  "content": "He stood before the sons of Heth,\nAnd bowed his sorrowing head;\n\n\"I've come,\" he said, \"to buy a place\nWhere I may lay my dead.\n\n\"I am a stranger in your land,\nMy home has lost its light;\nGrant me a place where I may lay\nMy dead away from sight.\"\n\nThen tenderly the sons of Heth\nGazed on the mourner's face,\nAnd said, \"Oh, Prince, amid our dead,\nChoose thou her resting-place.\n\n\"The sepulchres of those we love,\nWe place at thy command;\nAgainst the plea thy grief hath made\nWe close not heart nor hand.\"\n\nThe patriarch rose and bowed his head,\nAnd said, \"One place I crave;\n'Tis at the end of Ephron's field,\nAnd called Machpelah's cave.\n\n\"Entreat him that he sell to me\nFor her last sleep that cave;\nI do not ask for her I loved\nThe freedom of a grave.\"\n\nThe son of Zohar answered him,\n\"Hearken, my lord, to me;\nBefore our sons, the field and cave\nI freely give to thee.\"\n\n\"I will not take it as a gift,\"\nThe grand old man then said;\n\"I pray thee let me buy the place\nWhere I may lay my dead.\"\n\nAnd with the promise in his heart,\nHis seed should own that land,\nHe gave the shekels for the field\nHe took from Ephron's hand.\n\nAnd saw afar the glorious day\nHis chosen seed should tread,\nThe soil where he in sorrow lay\nHis loved and cherished dead.",
  "source": "Project Gutenberg, Poems (EBook #679)",
  "date": "1854-1901"
}