{
  "id": "rupert-brooke-1914-i-peace",
  "title": "1914 I: Peace",
  "author": "Rupert Brooke",
  "content": "Now, God be thanked Who has watched us with His hour,\nAnd caught our youth, and wakened us from sleeping,\nWith hand made sure, clear eye, and sharpened power,\nTo turn, as swimmers into cleanness leaping,\nGlad from a world grown old and cold and weary,\nLeave the sick hearts that honour could not move,\nAnd half-men, and their dirty songs and dreary,\nAnd all the little emptiness of love!\n\nOh! we, who have known shame, we have found release there,\nWhere there's no ill, no grief, but sleep has mending,\nNaught broken save this body, lost but breath;\nNothing to shake the laughing heart's long peace there\nBut only agony, and that has ending;\nAnd the worst friend and enemy is but Death.",
  "source": "PoetryDB / Project Gutenberg",
  "linecount": 14
}