{
  "id": "robert-browning-summum-bonum",
  "title": "Summum Bonum",
  "author": "Robert Browning",
  "content": "All the breath and the bloom of the year in the bag of one bee:\nAll the wonder and wealth of the mine in the heart of one gem:\nIn the core of one pearl all the shade and the shine of the sea:\nBreath and bloom, shade and shine,--wonder, wealth, and--how far above them--\n   Truth, that's brighter than gem,\n   Trust, that's purer than pearl,--\nBrightest truth, purest trust in the universe,--all were for me\n   In the kiss of one girl.",
  "source": "PoetryDB / Project Gutenberg",
  "linecount": 8
}