{
  "id": "rabindranath-tagore-gitanjali-xii",
  "title": "Gitanjali XII",
  "author": "Rabindranath Tagore",
  "content": "The time that my journey takes is long and the way of it long.\n\nI came out on the chariot of the first gleam of light, and pursued my\nvoyage through the wildernesses of worlds leaving my track on many a\nstar and planet.\n\nIt is the most distant course that comes nearest to thyself, and that\ntraining is the most intricate which leads to the utter simplicity of a\ntune.\n\nThe traveller has to knock at every alien door to come to his own, and\none has to wander through all the outer worlds to reach the innermost\nshrine at the end.\n\nMy eyes strayed far and wide before I shut them and said “Here art\nthou!”\n\nThe question and the cry “Oh, where?” melt into tears of a thousand\nstreams and deluge the world with the flood of the assurance “I am!”",
  "source": "Project Gutenberg, Gitanjali (EBook #7164)",
  "date": "1913"
}